gnssanalysis/__init__.py
gnssanalysis/_version.py
gnssanalysis/enum_meta_properties.py
gnssanalysis/filenames.py
gnssanalysis/format_types.py
gnssanalysis/gn_aux.py
gnssanalysis/gn_combi.py
gnssanalysis/gn_const.py
gnssanalysis/gn_datetime.py
gnssanalysis/gn_diffaux.py
gnssanalysis/gn_download.py
gnssanalysis/gn_frame.py
gnssanalysis/gn_plot.py
gnssanalysis/gn_transform.py
gnssanalysis/gn_utils.py
gnssanalysis/py.typed
gnssanalysis/solution_types.py
gnssanalysis/trim_sp3_util.py
gnssanalysis/gn_io/__init__.py
gnssanalysis/gn_io/aux_dicts.py
gnssanalysis/gn_io/bia.py
gnssanalysis/gn_io/blq.py
gnssanalysis/gn_io/clk.py
gnssanalysis/gn_io/common.py
gnssanalysis/gn_io/discon.py
gnssanalysis/gn_io/erp.py
gnssanalysis/gn_io/igslog.py
gnssanalysis/gn_io/ionex.py
gnssanalysis/gn_io/nanu.py
gnssanalysis/gn_io/pea.py
gnssanalysis/gn_io/pod.py
gnssanalysis/gn_io/psd.py
gnssanalysis/gn_io/rinex.py
gnssanalysis/gn_io/sinex.py
gnssanalysis/gn_io/sp3.py
gnssanalysis/gn_io/stec.py
gnssanalysis/gn_io/trace.py
gnssanalysis/gn_io/trop.py
gnssanalysis-0.0.59.dist-info/licenses/LICENSE
gnssanalysis-0.0.59.dist-info/METADATA
gnssanalysis-0.0.59.dist-info/WHEEL
gnssanalysis-0.0.59.dist-info/entry_points.txt
gnssanalysis-0.0.59.dist-info/top_level.txt
gnssanalysis-0.0.59.dist-info/RECORD
