Metadata-Version: 2.4
Name: gnssanalysis
Version: 0.0.59
Summary: basic python module for gnss analysis
Author: Geoscience Australia
Author-email: GNSSAnalysis@ga.gov.au
License-File: LICENSE
Requires-Dist: boto3
Requires-Dist: click
Requires-Dist: hatanaka
Requires-Dist: jinja2
Requires-Dist: matplotlib
Requires-Dist: numpy
Requires-Dist: pandas==2.3.3
Requires-Dist: plotext==4.2
Requires-Dist: plotly
Requires-Dist: pyfakefs
Requires-Dist: pymongo
Requires-Dist: pytest
Requires-Dist: requests
Requires-Dist: scipy
Requires-Dist: tqdm
Requires-Dist: unlzw3
Requires-Dist: typing_extensions
Dynamic: author
Dynamic: author-email
Dynamic: description
Dynamic: description-content-type
Dynamic: license-file
Dynamic: requires-dist
Dynamic: summary
